setup.py
uric/__init__.py
uric/__verison__.py
uric.egg-info/PKG-INFO
uric.egg-info/SOURCES.txt
uric.egg-info/dependency_links.txt
uric.egg-info/not-zip-safe
uric.egg-info/requires.txt
uric.egg-info/top_level.txt
uric/ali/__init__.py
uric/ali/api.py
uric/ali/tools.py
uric/ali/client/__init__.py
uric/ali/client/basic.py
uric/ali/client/api/__init__.py
uric/ali/client/api/certify.py
uric/ali/pay/__init__.py
uric/ali/pay/basic.py
uric/ali/pay/api/__init__.py
uric/ali/pay/api/app.py
uric/ali/pay/api/base.py
uric/ali/pay/api/order.py
uric/ali/pay/api/page.py
uric/ali/pay/api/transfer.py
uric/ali/pay/api/wap.py
uric/ali/yun/__init__.py
uric/ali/yun/basic.py
uric/ali/yun/api/__init__.py
uric/ali/yun/api/base.py
uric/ali/yun/api/sms.py
uric/ali/yun/api/vod.py
uric/wx/__init__.py
uric/wx/api.py
uric/wx/errcodes.py
uric/wx/templates.py
uric/wx/tools.py
uric/wx/client/__init__.py
uric/wx/client/basic.py
uric/wx/client/api/__init__.py
uric/wx/client/api/base.py
uric/wx/client/api/message.py
uric/wx/client/api/misc.py
uric/wx/client/api/users.py
uric/wx/others/__init__.py
uric/wx/others/oauth.py
uric/wx/pay/__init__.py
uric/wx/pay/basic.py
uric/wx/pay/api/__init__.py
uric/wx/pay/api/base.py
uric/wx/pay/api/jsapi.py
uric/wx/pay/api/order.py
uric/wx/pay/api/redpack.py
uric/wx/pay/api/refund.py
uric/wx/pay/api/tools.py