Metadata-Version: 1.1
Name: uric
Version: 1.2.1
Summary: ali and wx sdk for django.
Home-page: https://github.com/csrftoken/uric.git
Author: LiuZhiChao
Author-email: 404042726@qq.com
License: Apache 2
Platform: all
Classifier: Framework :: AsyncIO
Classifier: Environment :: Web Environment
Classifier: Intended Audience :: Developers
Classifier: License :: OSI Approved :: Apache Software License
Classifier: Operating System :: OS Independent
Classifier: Programming Language :: Python
Classifier: Programming Language :: Python :: 3
Classifier: Topic :: Internet :: WWW/HTTP :: Dynamic Content
Classifier: Topic :: Software Development :: Libraries :: Python Modules
